django_pydantic_field/__init__.py
django_pydantic_field/_internal/__init__.py
django_pydantic_field/_internal/_annotation_utils.py
django_pydantic_field/_migration_serializers.py
django_pydantic_field/compat/__init__.py
django_pydantic_field/compat/deprecation.py
django_pydantic_field/compat/django.py
django_pydantic_field/compat/imports.py
django_pydantic_field/compat/pydantic.py
django_pydantic_field/compat/typing.py
django_pydantic_field/fields.py
django_pydantic_field/fields.pyi
django_pydantic_field/forms.py
django_pydantic_field/py.typed
django_pydantic_field/rest_framework.py
django_pydantic_field/rest_framework.pyi
django_pydantic_field/types.py
django_pydantic_field/v1/__init__.py
django_pydantic_field/v1/fields.py
django_pydantic_field/v1/fields.pyi
django_pydantic_field/v1/forms.py
django_pydantic_field/v1/rest_framework.py
django_pydantic_field/v1/schema_utils.py
django_pydantic_field/v1/types.py
django_pydantic_field/v2/__init__.py
django_pydantic_field/v2/fields.py
django_pydantic_field/v2/fields.pyi
django_pydantic_field/v2/forms.py
django_pydantic_field/v2/rest_framework/__init__.py
django_pydantic_field/v2/rest_framework/fields.py
django_pydantic_field/v2/rest_framework/mixins.py
django_pydantic_field/v2/rest_framework/openapi.py
django_pydantic_field/v2/rest_framework/parsers.py
django_pydantic_field/v2/rest_framework/renderers.py
django_pydantic_field/v2/types.py
django_pydantic_field-0.5.2.dist-info/licenses/LICENSE
django_pydantic_field-0.5.2.dist-info/WHEEL
django_pydantic_field-0.5.2.dist-info/METADATA
django_pydantic_field-0.5.2.dist-info/RECORD
