Metadata-Version: 2.4
Name: django-pydantic-field
Version: 0.5.2
Summary: Type-Safe Pydantic Schemas for Django JSONFields
Keywords: django,pydantic,json,schema
Author: Savva Surenkov
Author-email: Savva Surenkov <savva@surenkov.space>
License-Expression: MIT
License-File: LICENSE
Classifier: Development Status :: 4 - Beta
Classifier: Intended Audience :: Developers
Classifier: Framework :: Django
Classifier: Framework :: Django :: 3
Classifier: Framework :: Django :: 3.1
Classifier: Framework :: Django :: 3.2
Classifier: Framework :: Django :: 4
Classifier: Framework :: Django :: 4.0
Classifier: Framework :: Django :: 4.1
Classifier: Framework :: Django :: 4.2
Classifier: Framework :: Django :: 5
Classifier: Framework :: Django :: 5.0
Classifier: Framework :: Django :: 5.1
Classifier: Framework :: Django :: 5.2
Classifier: Framework :: Django :: 6.0
Classifier: Framework :: Pydantic
Classifier: Framework :: Pydantic :: 1
Classifier: Framework :: Pydantic :: 2
Classifier: Programming Language :: Python
Classifier: Programming Language :: Python :: 3
Classifier: Programming Language :: Python :: 3 :: Only
Classifier: Programming Language :: Python :: 3.10
Classifier: Programming Language :: Python :: 3.11
Classifier: Programming Language :: Python :: 3.12
Classifier: Programming Language :: Python :: 3.13
Classifier: Programming Language :: Python :: 3.14
Requires-Dist: pydantic>=1.10,<3
Requires-Dist: django>=3.1
Requires-Dist: typing-extensions
Requires-Dist: django-jsonform>=2.0,<3 ; extra == 'jsonform'
Requires-Dist: uritemplate ; extra == 'openapi'
Requires-Dist: inflection ; extra == 'openapi'
Requires-Python: >=3.10
Project-URL: Homepage, https://github.com/surenkov/django-pydantic-field
Project-URL: Documentation, https://github.com/surenkov/django-pydantic-field
Project-URL: Source, https://github.com/surenkov/django-pydantic-field
Project-URL: Changelog, https://github.com/surenkov/django-pydantic-field/releases
Provides-Extra: jsonform
Provides-Extra: openapi
